[
  {
    "run": 1,
    "date": "2026-04-02",
    "predicted": [
      1,
      32,
      10,
      53,
      52,
      1
    ],
    "confidences": [
      0.0246,
      0.013,
      0.2645,
      0.0102,
      0.0358,
      0.2466
    ],
    "predicted_sum": 148,
    "regime": 1,
    "temperature": 8.0,
    "mean_sum": 151.61,
    "mode_sum": 138,
    "stddev": 37.74,
    "test_scores": {
      "1": 0.08108108108108109,
      "2": 0.02195945945945946,
      "3": 0.02702702702702703,
      "4": 0.030405405405405407,
      "5": 0.07094594594594594,
      "extra": 0.23479729729729729
    },
    "config": {
      "game_balls": [
        1,
        2,
        3,
        4,
        5
      ],
      "game_has_extra": true
    }
  },
  {
    "run": 3,
    "date": "2026-04-02",
    "predicted": [
      6,
      19,
      10,
      54,
      57,
      3
    ],
    "confidences": [
      0.0405,
      0.0118,
      0.2645,
      0.0148,
      0.0221,
      0.2453
    ],
    "predicted_sum": 146,
    "regime": 1,
    "temperature": 8.0,
    "mean_sum": 151.61,
    "mode_sum": 138,
    "stddev": 37.74,
    "test_scores": {
      "1": 0.08108108108108109,
      "2": 0.02195945945945946,
      "3": 0.02702702702702703,
      "4": 0.030405405405405407,
      "5": 0.07094594594594594,
      "extra": 0.23479729729729729
    },
    "config": {
      "game_balls": [
        1,
        2,
        3,
        4,
        5
      ],
      "game_has_extra": true
    }
  },
  {
    "run": 5,
    "date": "2026-04-02",
    "predicted": [
      4,
      38,
      32,
      56,
      27,
      4
    ],
    "confidences": [
      0.0253,
      0.0117,
      0.0119,
      0.0159,
      0.2622,
      0.2544
    ],
    "predicted_sum": 157,
    "regime": 1,
    "temperature": 8.0,
    "mean_sum": 151.61,
    "mode_sum": 138,
    "stddev": 37.74,
    "test_scores": {
      "1": 0.08108108108108109,
      "2": 0.02195945945945946,
      "3": 0.02702702702702703,
      "4": 0.030405405405405407,
      "5": 0.07094594594594594,
      "extra": 0.23479729729729729
    },
    "config": {
      "game_balls": [
        1,
        2,
        3,
        4,
        5
      ],
      "game_has_extra": true
    }
  },
  {
    "run": 6,
    "date": "2026-04-02",
    "predicted": [
      51,
      7,
      10,
      36,
      48,
      1
    ],
    "confidences": [
      0.0148,
      0.0211,
      0.2645,
      0.0175,
      0.022,
      0.2466
    ],
    "predicted_sum": 152,
    "regime": 1,
    "temperature": 8.0,
    "mean_sum": 151.61,
    "mode_sum": 138,
    "stddev": 37.74,
    "test_scores": {
      "1": 0.08108108108108109,
      "2": 0.02195945945945946,
      "3": 0.02702702702702703,
      "4": 0.030405405405405407,
      "5": 0.07094594594594594,
      "extra": 0.23479729729729729
    },
    "config": {
      "game_balls": [
        1,
        2,
        3,
        4,
        5
      ],
      "game_has_extra": true
    }
  },
  {
    "run": 10,
    "date": "2026-04-02",
    "predicted": [
      5,
      11,
      30,
      54,
      58,
      2
    ],
    "confidences": [
      0.0298,
      0.029,
      0.0256,
      0.0148,
      0.0177,
      0.2537
    ],
    "predicted_sum": 158,
    "regime": 1,
    "temperature": 8.0,
    "mean_sum": 151.61,
    "mode_sum": 138,
    "stddev": 37.74,
    "test_scores": {
      "1": 0.08108108108108109,
      "2": 0.02195945945945946,
      "3": 0.02702702702702703,
      "4": 0.030405405405405407,
      "5": 0.07094594594594594,
      "extra": 0.23479729729729729
    },
    "config": {
      "game_balls": [
        1,
        2,
        3,
        4,
        5
      ],
      "game_has_extra": true
    }
  }
]