[
  {
    "run": 1,
    "date": "2025-09-10",
    "predicted": [
      7,
      11,
      14,
      30,
      42
    ],
    "accuracy_scores": [
      0.8698,
      0.9171,
      0.9367,
      0.9317,
      0.934
    ],
    "predicted_sum": 104,
    "mean_sum": 105.65,
    "mode_sum": 111,
    "stddev": 26.07,
    "pass_checks": {
      "accuracy": true,
      "mean": true,
      "mode": true,
      "stddev": true
    },
    "predicted_main": [
      7,
      11,
      14,
      30
    ],
    "predicted_extra": [
      42
    ]
  },
  {
    "run": 2,
    "date": "2025-09-10",
    "predicted": [
      8,
      11,
      16,
      33,
      41
    ],
    "accuracy_scores": [
      0.8698,
      0.9171,
      0.9367,
      0.9317,
      0.934
    ],
    "predicted_sum": 109,
    "mean_sum": 105.65,
    "mode_sum": 111,
    "stddev": 26.07,
    "pass_checks": {
      "accuracy": true,
      "mean": true,
      "mode": true,
      "stddev": true
    },
    "predicted_main": [
      8,
      11,
      16,
      33
    ],
    "predicted_extra": [
      41
    ]
  },
  {
    "run": 3,
    "date": "2025-09-10",
    "predicted": [
      10,
      22,
      15,
      18,
      42
    ],
    "accuracy_scores": [
      0.8698,
      0.9171,
      0.9367,
      0.9317,
      0.934
    ],
    "predicted_sum": 107,
    "mean_sum": 105.65,
    "mode_sum": 111,
    "stddev": 26.07,
    "pass_checks": {
      "accuracy": true,
      "mean": true,
      "mode": true,
      "stddev": true
    },
    "predicted_main": [
      10,
      22,
      15,
      18
    ],
    "predicted_extra": [
      42
    ]
  },
  {
    "run": 4,
    "date": "2025-09-10",
    "predicted": [
      8,
      11,
      16,
      23,
      43
    ],
    "accuracy_scores": [
      0.8698,
      0.9171,
      0.9367,
      0.9317,
      0.934
    ],
    "predicted_sum": 101,
    "mean_sum": 105.65,
    "mode_sum": 111,
    "stddev": 26.07,
    "pass_checks": {
      "accuracy": true,
      "mean": true,
      "mode": true,
      "stddev": true
    },
    "predicted_main": [
      8,
      11,
      16,
      23
    ],
    "predicted_extra": [
      43
    ]
  },
  {
    "run": 5,
    "date": "2025-09-10",
    "predicted": [
      10,
      11,
      19,
      26,
      43
    ],
    "accuracy_scores": [
      0.8698,
      0.9171,
      0.9367,
      0.9317,
      0.934
    ],
    "predicted_sum": 109,
    "mean_sum": 105.65,
    "mode_sum": 111,
    "stddev": 26.07,
    "pass_checks": {
      "accuracy": true,
      "mean": true,
      "mode": true,
      "stddev": true
    },
    "predicted_main": [
      10,
      11,
      19,
      26
    ],
    "predicted_extra": [
      43
    ]
  },
  {
    "run": 6,
    "date": "2025-09-10",
    "predicted": [
      5,
      22,
      19,
      23,
      41
    ],
    "accuracy_scores": [
      0.8698,
      0.9171,
      0.9367,
      0.9317,
      0.934
    ],
    "predicted_sum": 110,
    "mean_sum": 105.65,
    "mode_sum": 111,
    "stddev": 26.07,
    "pass_checks": {
      "accuracy": true,
      "mean": true,
      "mode": true,
      "stddev": true
    },
    "predicted_main": [
      5,
      22,
      19,
      23
    ],
    "predicted_extra": [
      41
    ]
  },
  {
    "run": 7,
    "date": "2025-09-10",
    "predicted": [
      8,
      22,
      15,
      23,
      41
    ],
    "accuracy_scores": [
      0.8698,
      0.9171,
      0.9367,
      0.9317,
      0.934
    ],
    "predicted_sum": 109,
    "mean_sum": 105.65,
    "mode_sum": 111,
    "stddev": 26.07,
    "pass_checks": {
      "accuracy": true,
      "mean": true,
      "mode": true,
      "stddev": true
    },
    "predicted_main": [
      8,
      22,
      15,
      23
    ],
    "predicted_extra": [
      41
    ]
  },
  {
    "run": 8,
    "date": "2025-09-10",
    "predicted": [
      8,
      11,
      16,
      26,
      42
    ],
    "accuracy_scores": [
      0.8698,
      0.9171,
      0.9367,
      0.9317,
      0.934
    ],
    "predicted_sum": 103,
    "mean_sum": 105.65,
    "mode_sum": 111,
    "stddev": 26.07,
    "pass_checks": {
      "accuracy": true,
      "mean": true,
      "mode": true,
      "stddev": true
    },
    "predicted_main": [
      8,
      11,
      16,
      26
    ],
    "predicted_extra": [
      42
    ]
  },
  {
    "run": 9,
    "date": "2025-09-10",
    "predicted": [
      6,
      11,
      26,
      22,
      40
    ],
    "accuracy_scores": [
      0.8698,
      0.9171,
      0.9367,
      0.9317,
      0.934
    ],
    "predicted_sum": 105,
    "mean_sum": 105.65,
    "mode_sum": 111,
    "stddev": 26.07,
    "pass_checks": {
      "accuracy": true,
      "mean": true,
      "mode": true,
      "stddev": true
    },
    "predicted_main": [
      6,
      11,
      26,
      22
    ],
    "predicted_extra": [
      40
    ]
  },
  {
    "run": 10,
    "date": "2025-09-10",
    "predicted": [
      8,
      22,
      15,
      23,
      41
    ],
    "accuracy_scores": [
      0.8698,
      0.9171,
      0.9367,
      0.9317,
      0.934
    ],
    "predicted_sum": 109,
    "mean_sum": 105.65,
    "mode_sum": 111,
    "stddev": 26.07,
    "pass_checks": {
      "accuracy": true,
      "mean": true,
      "mode": true,
      "stddev": true
    },
    "predicted_main": [
      8,
      22,
      15,
      23
    ],
    "predicted_extra": [
      41
    ]
  }
]