[
  {
    "run": 1,
    "date": "2026-07-05",
    "predicted": [
      7,
      22,
      18,
      51,
      42,
      3
    ],
    "confidences": [
      0.0473,
      0.1471,
      0.0427,
      0.0338,
      0.0278,
      0.1949
    ],
    "predicted_sum": 140,
    "regime": 1,
    "temperature": 6.47773974743965,
    "mean_sum": 143.52,
    "mode_sum": 142,
    "stddev": 35.92,
    "test_scores": {
      "1": 0.037037037037037035,
      "2": 0.037037037037037035,
      "3": 0.0,
      "4": 0.0,
      "5": 0.07407407407407407,
      "extra": 0.2962962962962963
    },
    "config": {
      "game_balls": [
        1,
        2,
        3,
        4,
        5
      ],
      "game_has_extra": true
    }
  },
  {
    "run": 2,
    "date": "2026-07-05",
    "predicted": [
      8,
      22,
      12,
      47,
      57,
      3
    ],
    "confidences": [
      0.0521,
      0.1471,
      0.021,
      0.0406,
      0.1135,
      0.1949
    ],
    "predicted_sum": 146,
    "regime": 1,
    "temperature": 6.47773974743965,
    "mean_sum": 143.52,
    "mode_sum": 142,
    "stddev": 35.92,
    "test_scores": {
      "1": 0.037037037037037035,
      "2": 0.037037037037037035,
      "3": 0.0,
      "4": 0.0,
      "5": 0.07407407407407407,
      "extra": 0.2962962962962963
    },
    "config": {
      "game_balls": [
        1,
        2,
        3,
        4,
        5
      ],
      "game_has_extra": true
    }
  },
  {
    "run": 3,
    "date": "2026-07-05",
    "predicted": [
      6,
      15,
      25,
      42,
      58,
      1
    ],
    "confidences": [
      0.0431,
      0.0308,
      0.0459,
      0.0414,
      0.1312,
      0.1962
    ],
    "predicted_sum": 146,
    "regime": 1,
    "temperature": 6.47773974743965,
    "mean_sum": 143.52,
    "mode_sum": 142,
    "stddev": 35.92,
    "test_scores": {
      "1": 0.037037037037037035,
      "2": 0.037037037037037035,
      "3": 0.0,
      "4": 0.0,
      "5": 0.07407407407407407,
      "extra": 0.2962962962962963
    },
    "config": {
      "game_balls": [
        1,
        2,
        3,
        4,
        5
      ],
      "game_has_extra": true
    }
  },
  {
    "run": 4,
    "date": "2026-07-05",
    "predicted": [
      3,
      19,
      17,
      48,
      56,
      4
    ],
    "confidences": [
      0.0415,
      0.0372,
      0.0573,
      0.0322,
      0.0914,
      0.2001
    ],
    "predicted_sum": 143,
    "regime": 1,
    "temperature": 6.47773974743965,
    "mean_sum": 143.52,
    "mode_sum": 142,
    "stddev": 35.92,
    "test_scores": {
      "1": 0.037037037037037035,
      "2": 0.037037037037037035,
      "3": 0.0,
      "4": 0.0,
      "5": 0.07407407407407407,
      "extra": 0.2962962962962963
    },
    "config": {
      "game_balls": [
        1,
        2,
        3,
        4,
        5
      ],
      "game_has_extra": true
    }
  },
  {
    "run": 5,
    "date": "2026-07-05",
    "predicted": [
      2,
      29,
      30,
      33,
      51,
      5
    ],
    "confidences": [
      0.0421,
      0.0163,
      0.0231,
      0.025,
      0.0365,
      0.2127
    ],
    "predicted_sum": 145,
    "regime": 1,
    "temperature": 6.47773974743965,
    "mean_sum": 143.52,
    "mode_sum": 142,
    "stddev": 35.92,
    "test_scores": {
      "1": 0.037037037037037035,
      "2": 0.037037037037037035,
      "3": 0.0,
      "4": 0.0,
      "5": 0.07407407407407407,
      "extra": 0.2962962962962963
    },
    "config": {
      "game_balls": [
        1,
        2,
        3,
        4,
        5
      ],
      "game_has_extra": true
    }
  },
  {
    "run": 6,
    "date": "2026-07-05",
    "predicted": [
      28,
      17,
      18,
      39,
      35,
      4
    ],
    "confidences": [
      0.041,
      0.0895,
      0.0427,
      0.0297,
      0.0174,
      0.2001
    ],
    "predicted_sum": 137,
    "regime": 1,
    "temperature": 6.47773974743965,
    "mean_sum": 143.52,
    "mode_sum": 142,
    "stddev": 35.92,
    "test_scores": {
      "1": 0.037037037037037035,
      "2": 0.037037037037037035,
      "3": 0.0,
      "4": 0.0,
      "5": 0.07407407407407407,
      "extra": 0.2962962962962963
    },
    "config": {
      "game_balls": [
        1,
        2,
        3,
        4,
        5
      ],
      "game_has_extra": true
    }
  },
  {
    "run": 7,
    "date": "2026-07-05",
    "predicted": [
      7,
      44,
      18,
      31,
      47,
      3
    ],
    "confidences": [
      0.0473,
      0.0117,
      0.0427,
      0.0272,
      0.0352,
      0.1949
    ],
    "predicted_sum": 147,
    "regime": 1,
    "temperature": 6.47773974743965,
    "mean_sum": 143.52,
    "mode_sum": 142,
    "stddev": 35.92,
    "test_scores": {
      "1": 0.037037037037037035,
      "2": 0.037037037037037035,
      "3": 0.0,
      "4": 0.0,
      "5": 0.07407407407407407,
      "extra": 0.2962962962962963
    },
    "config": {
      "game_balls": [
        1,
        2,
        3,
        4,
        5
      ],
      "game_has_extra": true
    }
  },
  {
    "run": 8,
    "date": "2026-07-05",
    "predicted": [
      6,
      20,
      25,
      50,
      38,
      5
    ],
    "confidences": [
      0.0431,
      0.0745,
      0.0459,
      0.0507,
      0.0192,
      0.2127
    ],
    "predicted_sum": 139,
    "regime": 1,
    "temperature": 6.47773974743965,
    "mean_sum": 143.52,
    "mode_sum": 142,
    "stddev": 35.92,
    "test_scores": {
      "1": 0.037037037037037035,
      "2": 0.037037037037037035,
      "3": 0.0,
      "4": 0.0,
      "5": 0.07407407407407407,
      "extra": 0.2962962962962963
    },
    "config": {
      "game_balls": [
        1,
        2,
        3,
        4,
        5
      ],
      "game_has_extra": true
    }
  },
  {
    "run": 9,
    "date": "2026-07-05",
    "predicted": [
      7,
      20,
      28,
      41,
      45,
      3
    ],
    "confidences": [
      0.0473,
      0.0745,
      0.0238,
      0.0284,
      0.021,
      0.1949
    ],
    "predicted_sum": 141,
    "regime": 1,
    "temperature": 6.47773974743965,
    "mean_sum": 143.52,
    "mode_sum": 142,
    "stddev": 35.92,
    "test_scores": {
      "1": 0.037037037037037035,
      "2": 0.037037037037037035,
      "3": 0.0,
      "4": 0.0,
      "5": 0.07407407407407407,
      "extra": 0.2962962962962963
    },
    "config": {
      "game_balls": [
        1,
        2,
        3,
        4,
        5
      ],
      "game_has_extra": true
    }
  },
  {
    "run": 10,
    "date": "2026-07-05",
    "predicted": [
      12,
      13,
      9,
      50,
      54,
      4
    ],
    "confidences": [
      0.0423,
      0.0224,
      0.0269,
      0.0507,
      0.0959,
      0.2001
    ],
    "predicted_sum": 138,
    "regime": 1,
    "temperature": 6.47773974743965,
    "mean_sum": 143.52,
    "mode_sum": 142,
    "stddev": 35.92,
    "test_scores": {
      "1": 0.037037037037037035,
      "2": 0.037037037037037035,
      "3": 0.0,
      "4": 0.0,
      "5": 0.07407407407407407,
      "extra": 0.2962962962962963
    },
    "config": {
      "game_balls": [
        1,
        2,
        3,
        4,
        5
      ],
      "game_has_extra": true
    }
  },
  {
    "run": "consensus",
    "date": "2026-07-05",
    "predicted": [
      7,
      22,
      18,
      50,
      42,
      3
    ],
    "method": "majority_vote",
    "based_on_runs": 10
  }
]