[
  {
    "run": 1,
    "date": "2025-06-07",
    "predicted": [
      3,
      20,
      24,
      36,
      65,
      1
    ],
    "accuracy_scores": [
      0.8754,
      0.8381,
      0.8982,
      0.945,
      0.9816,
      1.0
    ],
    "predicted_sum": 149,
    "mean_sum": 154.59,
    "mode_sum": 158,
    "stddev": 43.63,
    "pass_checks": {
      "accuracy": true,
      "mean": true,
      "mode": true,
      "stddev": true
    },
    "predicted_main": [
      3,
      20,
      24,
      36,
      65
    ],
    "predicted_extra": [
      1
    ]
  },
  {
    "run": 2,
    "date": "2025-06-07",
    "predicted": [
      17,
      13,
      22,
      38,
      60,
      1
    ],
    "accuracy_scores": [
      0.8754,
      0.8381,
      0.8982,
      0.945,
      0.9816,
      1.0
    ],
    "predicted_sum": 151,
    "mean_sum": 154.59,
    "mode_sum": 158,
    "stddev": 43.63,
    "pass_checks": {
      "accuracy": true,
      "mean": true,
      "mode": true,
      "stddev": true
    },
    "predicted_main": [
      17,
      13,
      22,
      38,
      60
    ],
    "predicted_extra": [
      1
    ]
  },
  {
    "run": 3,
    "date": "2025-06-07",
    "predicted": [
      4,
      21,
      33,
      40,
      58,
      1
    ],
    "accuracy_scores": [
      0.8754,
      0.8381,
      0.8982,
      0.945,
      0.9816,
      1.0
    ],
    "predicted_sum": 157,
    "mean_sum": 154.59,
    "mode_sum": 158,
    "stddev": 43.63,
    "pass_checks": {
      "accuracy": true,
      "mean": true,
      "mode": true,
      "stddev": true
    },
    "predicted_main": [
      4,
      21,
      33,
      40,
      58
    ],
    "predicted_extra": [
      1
    ]
  },
  {
    "run": 4,
    "date": "2025-06-07",
    "predicted": [
      4,
      22,
      35,
      34,
      58,
      1
    ],
    "accuracy_scores": [
      0.8754,
      0.8381,
      0.8982,
      0.945,
      0.9816,
      1.0
    ],
    "predicted_sum": 154,
    "mean_sum": 154.59,
    "mode_sum": 158,
    "stddev": 43.63,
    "pass_checks": {
      "accuracy": true,
      "mean": true,
      "mode": true,
      "stddev": true
    },
    "predicted_main": [
      4,
      22,
      35,
      34,
      58
    ],
    "predicted_extra": [
      1
    ]
  },
  {
    "run": 5,
    "date": "2025-06-07",
    "predicted": [
      6,
      17,
      30,
      39,
      66,
      1
    ],
    "accuracy_scores": [
      0.8754,
      0.8381,
      0.8982,
      0.945,
      0.9816,
      1.0
    ],
    "predicted_sum": 159,
    "mean_sum": 154.59,
    "mode_sum": 158,
    "stddev": 43.63,
    "pass_checks": {
      "accuracy": true,
      "mean": true,
      "mode": true,
      "stddev": true
    },
    "predicted_main": [
      6,
      17,
      30,
      39,
      66
    ],
    "predicted_extra": [
      1
    ]
  },
  {
    "run": 6,
    "date": "2025-06-07",
    "predicted": [
      3,
      20,
      27,
      37,
      66,
      1
    ],
    "accuracy_scores": [
      0.8754,
      0.8381,
      0.8982,
      0.945,
      0.9816,
      1.0
    ],
    "predicted_sum": 154,
    "mean_sum": 154.59,
    "mode_sum": 158,
    "stddev": 43.63,
    "pass_checks": {
      "accuracy": true,
      "mean": true,
      "mode": true,
      "stddev": true
    },
    "predicted_main": [
      3,
      20,
      27,
      37,
      66
    ],
    "predicted_extra": [
      1
    ]
  },
  {
    "run": 7,
    "date": "2025-06-07",
    "predicted": [
      4,
      22,
      34,
      37,
      62,
      1
    ],
    "accuracy_scores": [
      0.8754,
      0.8381,
      0.8982,
      0.945,
      0.9816,
      1.0
    ],
    "predicted_sum": 160,
    "mean_sum": 154.59,
    "mode_sum": 158,
    "stddev": 43.63,
    "pass_checks": {
      "accuracy": true,
      "mean": true,
      "mode": true,
      "stddev": true
    },
    "predicted_main": [
      4,
      22,
      34,
      37,
      62
    ],
    "predicted_extra": [
      1
    ]
  },
  {
    "run": 8,
    "date": "2025-06-07",
    "predicted": [
      3,
      20,
      24,
      34,
      65,
      1
    ],
    "accuracy_scores": [
      0.8754,
      0.8381,
      0.8982,
      0.945,
      0.9816,
      1.0
    ],
    "predicted_sum": 147,
    "mean_sum": 154.59,
    "mode_sum": 158,
    "stddev": 43.63,
    "pass_checks": {
      "accuracy": true,
      "mean": true,
      "mode": true,
      "stddev": true
    },
    "predicted_main": [
      3,
      20,
      24,
      34,
      65
    ],
    "predicted_extra": [
      1
    ]
  },
  {
    "run": 9,
    "date": "2025-06-07",
    "predicted": [
      10,
      21,
      27,
      36,
      63,
      1
    ],
    "accuracy_scores": [
      0.8754,
      0.8381,
      0.8982,
      0.945,
      0.9816,
      1.0
    ],
    "predicted_sum": 158,
    "mean_sum": 154.59,
    "mode_sum": 158,
    "stddev": 43.63,
    "pass_checks": {
      "accuracy": true,
      "mean": true,
      "mode": true,
      "stddev": true
    },
    "predicted_main": [
      10,
      21,
      27,
      36,
      63
    ],
    "predicted_extra": [
      1
    ]
  },
  {
    "run": 10,
    "date": "2025-06-07",
    "predicted": [
      3,
      21,
      26,
      37,
      66,
      1
    ],
    "accuracy_scores": [
      0.8754,
      0.8381,
      0.8982,
      0.945,
      0.9816,
      1.0
    ],
    "predicted_sum": 154,
    "mean_sum": 154.59,
    "mode_sum": 158,
    "stddev": 43.63,
    "pass_checks": {
      "accuracy": true,
      "mean": true,
      "mode": true,
      "stddev": true
    },
    "predicted_main": [
      3,
      21,
      26,
      37,
      66
    ],
    "predicted_extra": [
      1
    ]
  }
]