[
  {
    "run": 1,
    "date": "2025-12-26",
    "predicted": [
      5,
      25,
      20,
      38,
      57,
      9
    ],
    "confidences": [
      0.32,
      0.11,
      0.1933,
      0.3067,
      0.1533,
      0.1967
    ],
    "predicted_sum": 154,
    "regime": 1,
    "temperature": 1.0,
    "mean_sum": 155.18,
    "mode_sum": 151,
    "stddev": 43.35,
    "test_scores": {
      "1": 0.5915492957746479,
      "2": 0.4225352112676056,
      "3": 0.3967136150234742,
      "4": 0.45539906103286387,
      "5": 0.5375586854460094,
      "extra": 0.5845070422535211
    },
    "config": {
      "game_balls": [
        1,
        2,
        3,
        4,
        5
      ],
      "game_has_extra": true
    }
  },
  {
    "run": 2,
    "date": "2025-12-26",
    "predicted": [
      9,
      4,
      41,
      25,
      68,
      5
    ],
    "confidences": [
      0.32,
      0.11,
      0.1933,
      0.3067,
      0.1533,
      0.1967
    ],
    "predicted_sum": 152,
    "regime": 1,
    "temperature": 1.0,
    "mean_sum": 155.18,
    "mode_sum": 151,
    "stddev": 43.35,
    "test_scores": {
      "1": 0.5915492957746479,
      "2": 0.4225352112676056,
      "3": 0.3967136150234742,
      "4": 0.45539906103286387,
      "5": 0.5375586854460094,
      "extra": 0.5845070422535211
    },
    "config": {
      "game_balls": [
        1,
        2,
        3,
        4,
        5
      ],
      "game_has_extra": true
    }
  },
  {
    "run": 3,
    "date": "2025-12-26",
    "predicted": [
      1,
      20,
      27,
      36,
      51,
      21
    ],
    "confidences": [
      0.3167,
      0.2133,
      0.1,
      0.08,
      0.0867,
      0.1333
    ],
    "predicted_sum": 156,
    "regime": 1,
    "temperature": 1.0,
    "mean_sum": 155.18,
    "mode_sum": 151,
    "stddev": 43.35,
    "test_scores": {
      "1": 0.5915492957746479,
      "2": 0.4225352112676056,
      "3": 0.3967136150234742,
      "4": 0.45539906103286387,
      "5": 0.5375586854460094,
      "extra": 0.5845070422535211
    },
    "config": {
      "game_balls": [
        1,
        2,
        3,
        4,
        5
      ],
      "game_has_extra": true
    }
  },
  {
    "run": 4,
    "date": "2025-12-26",
    "predicted": [
      13,
      11,
      26,
      31,
      66,
      15
    ],
    "confidences": [
      0.32,
      0.11,
      0.1933,
      0.3067,
      0.1533,
      0.1967
    ],
    "predicted_sum": 162,
    "regime": 1,
    "temperature": 1.0,
    "mean_sum": 155.18,
    "mode_sum": 151,
    "stddev": 43.35,
    "test_scores": {
      "1": 0.5915492957746479,
      "2": 0.4225352112676056,
      "3": 0.3967136150234742,
      "4": 0.45539906103286387,
      "5": 0.5375586854460094,
      "extra": 0.5845070422535211
    },
    "config": {
      "game_balls": [
        1,
        2,
        3,
        4,
        5
      ],
      "game_has_extra": true
    }
  },
  {
    "run": 5,
    "date": "2025-12-26",
    "predicted": [
      3,
      6,
      37,
      38,
      63,
      11
    ],
    "confidences": [
      0.32,
      0.11,
      0.1933,
      0.3067,
      0.1533,
      0.1967
    ],
    "predicted_sum": 158,
    "regime": 1,
    "temperature": 1.0,
    "mean_sum": 155.18,
    "mode_sum": 151,
    "stddev": 43.35,
    "test_scores": {
      "1": 0.5915492957746479,
      "2": 0.4225352112676056,
      "3": 0.3967136150234742,
      "4": 0.45539906103286387,
      "5": 0.5375586854460094,
      "extra": 0.5845070422535211
    },
    "config": {
      "game_balls": [
        1,
        2,
        3,
        4,
        5
      ],
      "game_has_extra": true
    }
  },
  {
    "run": 6,
    "date": "2025-12-26",
    "predicted": [
      9,
      10,
      36,
      45,
      57,
      4
    ],
    "confidences": [
      0.2267,
      0.17,
      0.11,
      0.0867,
      0.1233,
      0.1667
    ],
    "predicted_sum": 161,
    "regime": 1,
    "temperature": 1.0,
    "mean_sum": 155.18,
    "mode_sum": 151,
    "stddev": 43.35,
    "test_scores": {
      "1": 0.5915492957746479,
      "2": 0.4225352112676056,
      "3": 0.3967136150234742,
      "4": 0.45539906103286387,
      "5": 0.5375586854460094,
      "extra": 0.5845070422535211
    },
    "config": {
      "game_balls": [
        1,
        2,
        3,
        4,
        5
      ],
      "game_has_extra": true
    }
  },
  {
    "run": 7,
    "date": "2025-12-26",
    "predicted": [
      3,
      7,
      26,
      53,
      47,
      12
    ],
    "confidences": [
      0.32,
      0.11,
      0.1933,
      0.3067,
      0.1533,
      0.1967
    ],
    "predicted_sum": 148,
    "regime": 1,
    "temperature": 1.0,
    "mean_sum": 155.18,
    "mode_sum": 151,
    "stddev": 43.35,
    "test_scores": {
      "1": 0.5915492957746479,
      "2": 0.4225352112676056,
      "3": 0.3967136150234742,
      "4": 0.45539906103286387,
      "5": 0.5375586854460094,
      "extra": 0.5845070422535211
    },
    "config": {
      "game_balls": [
        1,
        2,
        3,
        4,
        5
      ],
      "game_has_extra": true
    }
  },
  {
    "run": 8,
    "date": "2025-12-26",
    "predicted": [
      6,
      27,
      29,
      32,
      56,
      4
    ],
    "confidences": [
      0.2333,
      0.0867,
      0.1,
      0.1367,
      0.16,
      0.2133
    ],
    "predicted_sum": 154,
    "regime": 1,
    "temperature": 1.0,
    "mean_sum": 155.18,
    "mode_sum": 151,
    "stddev": 43.35,
    "test_scores": {
      "1": 0.5915492957746479,
      "2": 0.4225352112676056,
      "3": 0.3967136150234742,
      "4": 0.45539906103286387,
      "5": 0.5375586854460094,
      "extra": 0.5845070422535211
    },
    "config": {
      "game_balls": [
        1,
        2,
        3,
        4,
        5
      ],
      "game_has_extra": true
    }
  },
  {
    "run": 9,
    "date": "2025-12-26",
    "predicted": [
      11,
      20,
      8,
      37,
      68,
      18
    ],
    "confidences": [
      0.2033,
      0.09,
      0.5133,
      0.0967,
      0.1267,
      0.1067
    ],
    "predicted_sum": 162,
    "regime": 1,
    "temperature": 1.0,
    "mean_sum": 155.18,
    "mode_sum": 151,
    "stddev": 43.35,
    "test_scores": {
      "1": 0.5915492957746479,
      "2": 0.4225352112676056,
      "3": 0.3967136150234742,
      "4": 0.45539906103286387,
      "5": 0.5375586854460094,
      "extra": 0.5845070422535211
    },
    "config": {
      "game_balls": [
        1,
        2,
        3,
        4,
        5
      ],
      "game_has_extra": true
    }
  },
  {
    "run": 10,
    "date": "2025-12-26",
    "predicted": [
      6,
      17,
      30,
      36,
      52,
      10
    ],
    "confidences": [
      0.2333,
      0.0867,
      0.1,
      0.1367,
      0.16,
      0.2133
    ],
    "predicted_sum": 151,
    "regime": 1,
    "temperature": 1.0,
    "mean_sum": 155.18,
    "mode_sum": 151,
    "stddev": 43.35,
    "test_scores": {
      "1": 0.5915492957746479,
      "2": 0.4225352112676056,
      "3": 0.3967136150234742,
      "4": 0.45539906103286387,
      "5": 0.5375586854460094,
      "extra": 0.5845070422535211
    },
    "config": {
      "game_balls": [
        1,
        2,
        3,
        4,
        5
      ],
      "game_has_extra": true
    }
  }
]